README.md
setup.py
atspy/__init__.py
atspy/nbeats.py
atspy/pyaf.py
atspy/ssa.py
atspy.egg-info/PKG-INFO
atspy.egg-info/SOURCES.txt
atspy.egg-info/dependency_links.txt
atspy.egg-info/not-zip-safe
atspy.egg-info/top_level.txt